sendsafely/Package.py
sendsafely/Progress.py
sendsafely/SendSafely.py
sendsafely/__init__.py
sendsafely/exceptions.py
sendsafely/utilities.py
sendsafelyaftrdrk-1.0.1.dist-info/METADATA
sendsafelyaftrdrk-1.0.1.dist-info/WHEEL
sendsafelyaftrdrk-1.0.1.dist-info/top_level.txt
sendsafelyaftrdrk-1.0.1.dist-info/RECORD
