Metadata-Version: 2.1
Name: sendsafelyaftrdrk
Version: 1.0.1
Summary: The SendSafely Client API allows programmatic access to SendSafely and provides a layer of abstraction from our REST API, which requires developers to perform several complex tasks in a correct manner.
Home-page: https://github.com/SendSafely/Python-Client-API
Author: SendSafely
Author-email: support@sendsafely.com
Classifier: Development Status :: 5 - Production/Stable
Classifier: Intended Audience :: Developers
Classifier: Topic :: Software Development :: Libraries :: Application Frameworks
Classifier: Programming Language :: Python :: 3
Requires-Python: >=3
Requires-Dist: requests
Requires-Dist: PGPy
